{
  "generatedAt": "2026-04-15T11:33:37.131Z",
  "menuItems": [
    {
      "id": "ex6",
      "name": "Basil Pesto",
      "price": 45,
      "category": "Add Extras",
      "active": true
    },
    {
      "id": "ex1",
      "name": "Cheese",
      "price": 30,
      "category": "Add Extras",
      "active": true
    },
    {
      "id": "ex3",
      "name": "Cheese Burst",
      "price": 60,
      "category": "Add Extras",
      "active": true
    },
    {
      "id": "ex2",
      "name": "Chicken",
      "price": 40,
      "category": "Add Extras",
      "active": true
    },
    {
      "id": "ex7",
      "name": "Chilli Oil",
      "price": 35,
      "category": "Add Extras",
      "active": true
    },
    {
      "id": "ex5",
      "name": "Extra Virgin Olive Oil",
      "price": 30,
      "category": "Add Extras",
      "active": true
    },
    {
      "id": "ex4",
      "name": "Olive Oil",
      "price": 30,
      "category": "Add Extras",
      "active": true
    },
    {
      "id": "clz5",
      "name": "Cheesy Garlic Bread",
      "price": 130,
      "category": "Calzone",
      "active": true
    },
    {
      "id": "clz2",
      "name": "Chicken Loaded Calzone",
      "price": 230,
      "category": "Calzone",
      "active": true
    },
    {
      "id": "clz4",
      "name": "Choco Lava Calzone",
      "price": 199,
      "category": "Calzone",
      "active": true
    },
    {
      "id": "clz3",
      "name": "Ocean Bite Calzone",
      "price": 280,
      "category": "Calzone",
      "active": true
    },
    {
      "id": "clz1",
      "name": "Paneer Pocket Calzone",
      "price": 199,
      "category": "Calzone",
      "active": true
    },
    {
      "id": "cf2-12",
      "name": "BBQ Chicken Blaze 12\"",
      "price": 510,
      "category": "Chicken Favorites",
      "active": true
    },
    {
      "id": "cf2-9",
      "name": "BBQ Chicken Blaze 9\"",
      "price": 319,
      "category": "Chicken Favorites",
      "active": true
    },
    {
      "id": "cf4",
      "name": "Classic Pulled Chicken",
      "price": 459,
      "category": "Chicken Favorites",
      "active": true
    },
    {
      "id": "cf6",
      "name": "Pepperoni Heatwave",
      "price": 559,
      "category": "Chicken Favorites",
      "active": true
    },
    {
      "id": "cf3",
      "name": "Sizzling Chicken Sausage",
      "price": 429,
      "category": "Chicken Favorites",
      "active": true
    },
    {
      "id": "cf5",
      "name": "Spicy Chicken Tikka Rush",
      "price": 519,
      "category": "Chicken Favorites",
      "active": true
    },
    {
      "id": "cf1-12",
      "name": "Tandoori Chicken Inferno 12\"",
      "price": 519,
      "category": "Chicken Favorites",
      "active": true
    },
    {
      "id": "cf1-9",
      "name": "Tandoori Chicken Inferno 9\"",
      "price": 309,
      "category": "Chicken Favorites",
      "active": true
    },
    {
      "id": "c4",
      "name": "Basil Pesto Bliss",
      "price": 429,
      "category": "Classic",
      "active": true
    },
    {
      "id": "c3-12",
      "name": "Farm Fresh 12\"",
      "price": 319,
      "category": "Classic",
      "active": true
    },
    {
      "id": "c3-9",
      "name": "Farm Fresh 9\"",
      "price": 189,
      "category": "Classic",
      "active": true
    },
    {
      "id": "c2-12",
      "name": "Golden Corn Melt 12\"",
      "price": 299,
      "category": "Classic",
      "active": true
    },
    {
      "id": "c2-9",
      "name": "Golden Corn Melt 9\"",
      "price": 179,
      "category": "Classic",
      "active": true
    },
    {
      "id": "c1-12",
      "name": "Margherita 12\"",
      "price": 259,
      "category": "Classic",
      "active": true
    },
    {
      "id": "c1-9",
      "name": "Margherita 9\"",
      "price": 159,
      "category": "Classic",
      "active": true
    },
    {
      "id": "fs1",
      "name": "Double Chicken Overload",
      "price": 619,
      "category": "Fuego Signature",
      "active": true
    },
    {
      "id": "fs2",
      "name": "Feast Supreme",
      "price": 699,
      "category": "Fuego Signature",
      "active": true
    },
    {
      "id": "fs3",
      "name": "Ocean Flame Seafood Pizza",
      "price": 649,
      "category": "Fuego Signature",
      "active": true
    },
    {
      "id": "pp2",
      "name": "Chicken Tandoori Pocket",
      "price": 199,
      "category": "Pizza Pockets",
      "active": true
    },
    {
      "id": "pp1",
      "name": "Paneer Tikka Pocket",
      "price": 175,
      "category": "Pizza Pockets",
      "active": true
    },
    {
      "id": "pp3",
      "name": "Pepperoni Pocket Bites",
      "price": 219,
      "category": "Pizza Pockets",
      "active": true
    },
    {
      "id": "vd1-12",
      "name": "Butter Mushroom Magic 12\"",
      "price": 429,
      "category": "Veg Delights",
      "active": true
    },
    {
      "id": "vd1-9",
      "name": "Butter Mushroom Magic 9\"",
      "price": 309,
      "category": "Veg Delights",
      "active": true
    },
    {
      "id": "vd3",
      "name": "Desi Masala Paneer Feast",
      "price": 439,
      "category": "Veg Delights",
      "active": true
    },
    {
      "id": "vd2-12",
      "name": "Royal Tandoori Paneer 12\"",
      "price": 419,
      "category": "Veg Delights",
      "active": true
    },
    {
      "id": "vd2-9",
      "name": "Royal Tandoori Paneer 9\"",
      "price": 309,
      "category": "Veg Delights",
      "active": true
    },
    {
      "id": "vd4",
      "name": "Tandoori Paneer Fire",
      "price": 399,
      "category": "Veg Delights",
      "active": true
    }
  ],
  "orders": [
    {
      "id": "15-04-26-0002",
      "subtotal": 120,
      "discount": 0,
      "gst": 0,
      "total": 120,
      "tableNumber": "",
      "customerName": "",
      "customerPhone": "",
      "note": "",
      "timestamp": "2026-04-15T10:55:15.529Z",
      "payment": {
        "method": "Split",
        "amountPaid": 120,
        "tenderedAmount": 0,
        "status": "Paid",
        "due": 0,
        "change": 0,
        "splits": [
          {
            "method": "Cash",
            "account": "cash",
            "amount": 60
          },
          {
            "method": "UPI",
            "account": "upi_digital",
            "amount": 60
          }
        ],
        "settledAt": "2026-04-15T10:55:43.694Z"
      },
      "receiptSettings": {
        "restaurantName": "FUEGO",
        "address": "123 Oven Street, Crust City",
        "phone": "+91 9876543210",
        "gstEnabled": false,
        "gstNumber": "",
        "gstRate": 5,
        "printerModel": "RP326",
        "paperWidth": "80mm (3\")"
      },
      "items": [
        {
          "id": "ex6",
          "itemId": "ex6",
          "name": "Basil Pesto",
          "price": 45,
          "quantity": 2,
          "note": ""
        },
        {
          "id": "ex1",
          "itemId": "ex1",
          "name": "Cheese",
          "price": 30,
          "quantity": 1,
          "note": ""
        }
      ]
    },
    {
      "id": "15-04-26-0001",
      "subtotal": 85,
      "discount": 0,
      "gst": 0,
      "total": 85,
      "tableNumber": "",
      "customerName": "",
      "customerPhone": "",
      "note": "",
      "timestamp": "2026-04-15T10:48:28.234Z",
      "payment": {
        "method": "UPI",
        "amountPaid": 85,
        "tenderedAmount": 85,
        "status": "Paid",
        "account": "upi_digital",
        "due": 0,
        "change": 0
      },
      "receiptSettings": {
        "restaurantName": "FUEGO",
        "address": "123 Oven Street, Crust City",
        "phone": "+91 9876543210",
        "gstEnabled": false,
        "gstNumber": "",
        "gstRate": 5,
        "printerModel": "RP326",
        "paperWidth": "80mm (3\")"
      },
      "items": [
        {
          "id": "ex6",
          "itemId": "ex6",
          "name": "Basil Pesto",
          "price": 45,
          "quantity": 1,
          "note": ""
        },
        {
          "id": "ex2",
          "itemId": "ex2",
          "name": "Chicken",
          "price": 40,
          "quantity": 1,
          "note": ""
        }
      ]
    }
  ],
  "settings": {
    "null": null,
    "address": "123 Oven Street, Crust City",
    "gstEnabled": false,
    "gstNumber": "",
    "gstRate": 5,
    "logo": null,
    "paperWidth": "80mm (3\")",
    "phone": "+91 9876543210",
    "printerModel": "RP326",
    "restaurantName": "FUEGO"
  },
  "ledgerAdjustments": []
}
